Pipify_Components_Package/__init__.py
Pipify_Components_Package/rabbitmq_adapter.py
Pipify_Components_Package-0.0.1.dist-info/METADATA
Pipify_Components_Package-0.0.1.dist-info/WHEEL
Pipify_Components_Package-0.0.1.dist-info/top_level.txt
Pipify_Components_Package-0.0.1.dist-info/RECORD
