Metadata-Version: 2.1
Name: Pipify-Components-Package
Version: 0.0.1
Summary: Pipify_Components_Package
Home-page: UNKNOWN
Author: ORION
Author-email: datacollection@liferaftinc.com
License: UNKNOWN
Platform: UNKNOWN
Requires-Dist: pika
